typing_compat.py
typing_compat-0.1.0.dist-info/LICENSE-APACHE
typing_compat-0.1.0.dist-info/LICENSE-MIT
typing_compat-0.1.0.dist-info/METADATA
typing_compat-0.1.0.dist-info/WHEEL
typing_compat-0.1.0.dist-info/top_level.txt
typing_compat-0.1.0.dist-info/RECORD
