Metadata-Version: 2.1
Name: typing-compat
Version: 0.1.0
Summary: Python typing compatibility library
Home-page: https://github.com/rossmacarthur/typing-compat
Author: Ross MacArthur
Author-email: ross@macarthur.io
License: UNKNOWN
Download-URL: https://github.com/rossmacarthur/typing-compat/archive/0.1.0.tar.gz
Project-URL: Issue Tracker, https://github.com/rossmacarthur/typing-compat/issues
Platform: UNKNOWN
Classifier: Development Status :: 3 - Alpha
Classifier: License :: OSI Approved :: Apache Software License
Classifier: License :: OSI Approved :: MIT License
Classifier: Natural Language :: English
Classifier: Programming Language :: Python
Classifier: Programming Language :: Python :: 2
Classifier: Programming Language :: Python :: 2.7
Classifier: Programming Language :: Python :: 3
Classifier: Programming Language :: Python :: 3.5
Classifier: Programming Language :: Python :: 3.6
Classifier: Programming Language :: Python :: 3.7
Classifier: Programming Language :: Python :: 3.8
Classifier: Programming Language :: Python :: Implementation :: CPython
Classifier: Programming Language :: Python :: Implementation :: PyPy
Requires-Python: >=2.7, !=3.0.*, !=3.1.*, !=3.2.*, !=3.3.*, !=3.4.*
